culting/__init__.py
culting/__main__.py
culting/cli.py
culting/py.typed
culting/sh.py
culting-0.2.1.dist-info/LICENSE
culting-0.2.1.dist-info/METADATA
culting-0.2.1.dist-info/WHEEL
culting-0.2.1.dist-info/entry_points.txt
culting-0.2.1.dist-info/top_level.txt
culting-0.2.1.dist-info/RECORD
